fastcs_pandablocks/__init__.py
fastcs_pandablocks/__main__.py
fastcs_pandablocks/_version.py
fastcs_pandablocks/panda/__init__.py
fastcs_pandablocks/panda/client_wrapper.py
fastcs_pandablocks/panda/controller.yaml
fastcs_pandablocks/panda/panda_controller.py
fastcs_pandablocks/panda/utils.py
fastcs_pandablocks/panda/blocks/__init__.py
fastcs_pandablocks/panda/blocks/block_controller.py
fastcs_pandablocks/panda/blocks/blocks.py
fastcs_pandablocks/panda/blocks/data.py
fastcs_pandablocks/panda/blocks/versions.py
fastcs_pandablocks/panda/io/arm.py
fastcs_pandablocks/panda/io/bits.py
fastcs_pandablocks/panda/io/default.py
fastcs_pandablocks/panda/io/table.py
fastcs_pandablocks/panda/io/units.py
fastcs_pandablocks/types/__init__.py
fastcs_pandablocks/types/_annotations.py
fastcs_pandablocks/types/_string_types.py
fastcs_pandablocks-0.1.0.dist-info/licenses/LICENSE
fastcs_pandablocks-0.1.0.dist-info/METADATA
fastcs_pandablocks-0.1.0.dist-info/WHEEL
fastcs_pandablocks-0.1.0.dist-info/entry_points.txt
fastcs_pandablocks-0.1.0.dist-info/top_level.txt
fastcs_pandablocks-0.1.0.dist-info/RECORD
