Metadata-Version: 2.4
Name: fastcs-pandablocks
Version: 0.1.0
Summary: A softioc to control a PandABlocks-FPGA.
Author-email: Eva Lott <eva.lott@diamond.ac.uk>
License:                                  Apache License
Project-URL: GitHub, https://github.com/PandABlocks/fastcs-PandABlocks
Classifier: Development Status :: 3 - Alpha
Classifier: License :: OSI Approved :: Apache Software License
Classifier: Programming Language :: Python :: 3.11
Classifier: Programming Language :: Python :: 3.12
Requires-Python: >=3.11
License-File: LICENSE
Requires-Dist: fastcs[epicspva]~=0.11.1
Requires-Dist: pandablocks~=0.10.0
Requires-Dist: numpy<2
Requires-Dist: pydantic>2
Requires-Dist: h5py
Provides-Extra: dev
Requires-Dist: copier; extra == "dev"
Requires-Dist: myst-parser; extra == "dev"
Requires-Dist: pipdeptree; extra == "dev"
Requires-Dist: pre-commit; extra == "dev"
Requires-Dist: pydata-sphinx-theme>=0.12; extra == "dev"
Requires-Dist: pyright; extra == "dev"
Requires-Dist: pytest; extra == "dev"
Requires-Dist: pytest-asyncio; extra == "dev"
Requires-Dist: pytest-cov; extra == "dev"
Requires-Dist: pytest-mock; extra == "dev"
Requires-Dist: ruff; extra == "dev"
Requires-Dist: sphinx-autobuild; extra == "dev"
Requires-Dist: sphinx-copybutton; extra == "dev"
Requires-Dist: sphinx-design; extra == "dev"
Requires-Dist: tox-direct; extra == "dev"
Requires-Dist: types-mock; extra == "dev"
Dynamic: license-file
